Ansyas/MAS_models.py
Ansyas/__init__.py
Ansyas/ansyas.py
Ansyas/ansyas_mas_loader.py
Ansyas/ansyas_utils.py
Ansyas/bobbin.py
Ansyas/coil.py
Ansyas/cooling.py
Ansyas/core.py
Ansyas/excitation.py
Ansyas/mas_autocomplete.py
Ansyas/outputs.py
Ansyas/outputs/My_custom_magnetic_1761206547.0656064.aedt
Ansyas/outputs/My_custom_magnetic_1761206547.0656064.aedt.lock
Ansyas/outputs/My_custom_magnetic_1761206653.2642634.aedt
Ansyas/outputs/My_custom_magnetic_1761206653.2642634.aedt.lock
Ansyas/outputs/My_custom_magnetic_1761206732.1675286.aedt
Ansyas/outputs/My_custom_magnetic_1761206732.1675286.aedt.lock
Ansyas/outputs/My_custom_magnetic_1761206815.7405474.aedt
Ansyas/outputs/My_custom_magnetic_1761206815.7405474.aedt.lock
Ansyas/outputs/My_custom_magnetic_1761206547.0656064.aedtresults/.Maxwell 3D_WHL.asol.semaphore
Ansyas/outputs/My_custom_magnetic_1761206547.0656064.aedtresults/.Maxwell 3D_WHL.asol_priv.semaphore
Ansyas/outputs/My_custom_magnetic_1761206547.0656064.aedtresults/ManagedFiles_Design0.asol
Ansyas/outputs/My_custom_magnetic_1761206547.0656064.aedtresults/Maxwell 3D_WHL.asol
Ansyas/outputs/My_custom_magnetic_1761206547.0656064.aedtresults/Maxwell 3D_WHL.asol_priv
Ansyas/outputs/My_custom_magnetic_1761206547.0656064.aedtresults/mf_0/GeometryCache/CacheDataVersion.tmp
Ansyas/outputs/My_custom_magnetic_1761206547.0656064.aedtresults/mf_0/GeometryCache/InterrogationCache.tmp
Ansyas/outputs/My_custom_magnetic_1761206547.0656064.aedtresults/mf_0/GeometryCache/OperationDataCache.tmp
Ansyas/outputs/My_custom_magnetic_1761206547.0656064.aedtresults/mf_0/GeometryCache/BodyCache/0000006.fct
Ansyas/outputs/My_custom_magnetic_1761206547.0656064.aedtresults/mf_0/GeometryCache/BodyCache/0000006.x_b
Ansyas/outputs/My_custom_magnetic_1761206547.0656064.aedtresults/mf_0/GeometryCache/BodyCache/0000086.fct
Ansyas/outputs/My_custom_magnetic_1761206547.0656064.aedtresults/mf_0/GeometryCache/BodyCache/0000086.x_b
ansyas-0.9.11.dist-info/METADATA
ansyas-0.9.11.dist-info/WHEEL
ansyas-0.9.11.dist-info/licenses/LICENSE
ansyas-0.9.11.dist-info/RECORD
