Metadata-Version: 2.4
Name: Ansyas
Version: 0.9.11
Summary: Ansyas automates the 3D simulation in Ansys Maxwell and Icepak of any magnetic component described in MAS language.
Project-URL: Homepage, https://we-online.com
Project-URL: Repository, https://github.com/WurthElektronik/Ansyas
Project-URL: Contact, https://www.linkedin.com/in/alfonso-martinez-de-la-torre/
Author-email: Alfonso Martinez <Alfonso.Martinez@we-online.com>
License-Expression: MIT
License-File: LICENSE
Classifier: Development Status :: 4 - Beta
Classifier: Programming Language :: Python
Classifier: Programming Language :: Python :: 3.8
Classifier: Programming Language :: Python :: 3.9
Classifier: Programming Language :: Python :: 3.10
Classifier: Programming Language :: Python :: 3.11
Classifier: Programming Language :: Python :: 3.12
Classifier: Programming Language :: Python :: Implementation :: CPython
Classifier: Programming Language :: Python :: Implementation :: PyPy
Requires-Python: >=3.8
Requires-Dist: cadquery
Requires-Dist: numpy
Requires-Dist: openmagneticsvirtualbuilder
Requires-Dist: pyaedt
Requires-Dist: pymkf
